<?xml version="1.0" encoding="UTF-8"?>
<!DOCTYPE mapper PUBLIC "-//mybatis.org//DTD Mapper 3.0//EN" "http://mybatis.org/dtd/mybatis-3-mapper.dtd">
<mapper namespace="com.school.management.mapper.ClassSizeStandardMapper">

    <resultMap id="BaseResultMap" type="com.school.management.entity.ClassSizeStandard">
        <id column="id" property="id"/>
        <result column="semester_id" property="semesterId"/>
        <result column="department_id" property="departmentId"/>
        <result column="grade_level" property="gradeLevel"/>
        <result column="standard_size" property="standardSize"/>
        <result column="locked" property="locked"/>
        <result column="calculation_method" property="calculationMethod"/>
        <result column="locked_at" property="lockedAt"/>
        <result column="locked_by" property="lockedBy"/>
        <result column="remark" property="remark"/>
        <result column="created_at" property="createdAt"/>
        <result column="updated_at" property="updatedAt"/>
    </resultMap>

    <sql id="Base_Column_List">
        id, semester_id, department_id, grade_level, standard_size, locked,
        calculation_method, locked_at, locked_by, remark, created_at, updated_at
    </sql>

    <!-- 查询标准人数(按优先级) -->
    <select id="selectStandardSize" resultMap="BaseResultMap">
        SELECT
        <include refid="Base_Column_List"/>
        FROM class_size_standards
        WHERE semester_id = #{semesterId}
        AND (
        (department_id = #{departmentId} AND grade_level = #{gradeLevel})
        OR (department_id = #{departmentId} AND grade_level IS NULL)
        OR (department_id IS NULL AND grade_level IS NULL)
        )
        ORDER BY
        CASE
        WHEN department_id IS NOT NULL AND grade_level IS NOT NULL THEN 1
        WHEN department_id IS NOT NULL AND grade_level IS NULL THEN 2
        WHEN department_id IS NULL AND grade_level IS NULL THEN 3
        ELSE 4
        END,
        created_at DESC
        LIMIT 1
    </select>

    <!-- 查询学期的所有标准人数配置 -->
    <select id="selectBySemesterId" resultMap="BaseResultMap">
        SELECT
        <include refid="Base_Column_List"/>
        FROM class_size_standards
        WHERE semester_id = #{semesterId}
        ORDER BY
        department_id NULLS LAST,
        grade_level NULLS LAST,
        created_at DESC
    </select>

    <!-- 锁定标准人数 -->
    <update id="lockStandard">
        UPDATE class_size_standards
        SET locked    = 1,
            locked_at = NOW(),
            locked_by = #{lockedBy},
            updated_at = NOW()
        WHERE id = #{id}
    </update>

    <!-- 解锁标准人数 -->
    <update id="unlockStandard">
        UPDATE class_size_standards
        SET locked     = 0,
            locked_at  = NULL,
            locked_by  = NULL,
            updated_at = NOW()
        WHERE id = #{id}
    </update>

</mapper>
